<?xml version="1.0"?>
<ArticulatorSettings xmlns:xsi="http://www.w3.org/2001/XMLSchema-instance" xmlns:xsd="http://www.w3.org/2001/XMLSchema">
	<AnteriorPosteriorDistance>129</AnteriorPosteriorDistance>
	<IntercondylarDistance>110</IntercondylarDistance>
	<HeightUpperArticulatorPart>91.05</HeightUpperArticulatorPart>
	<HeightFrontPlate>0.001</HeightFrontPlate>
	<HeightIncisalNeedle>0</HeightIncisalNeedle>
	<ArticulatorPosition>
		<x>30</x>
		<y>-80</y>
		<z>-31</z>
	</ArticulatorPosition>
	<ArticulationPlaneLegRight>
		<x>-75</x>
		<y>13</y>
		<z>53</z>
	</ArticulationPlaneLegRight>
	<ArticulationPlaneLegLeft>
		<x>75</x>
		<y>13</y>
		<z>53</z>
	</ArticulationPlaneLegLeft>
	<ArticulationPlaneIncisalNeedle>
		<x>0</x>
		<y>2</y>
		<z>43.5</z>
	</ArticulationPlaneIncisalNeedle>
	<ArticulationPlaneVisualization>
		<TextureFileName>exocad_Texture_Plane.png</TextureFileName>
		<Material>
			<!--optional; same as ColorDefinition in defaultcolors.xml; except for opacity ignored if TextureFileName is defined -->
			<Color>#0000FF</Color>
			<Opacity>0.5</Opacity>
			<!--opacity settings-->
		</Material>
		<StippleTransparency>false</StippleTransparency>
		<!-- optional, default = false -->
	</ArticulationPlaneVisualization>
	<MovementregisterToArticulatorTransformation>
		<_00>-1</_00>
		<_01>0</_01>
		<_02>0</_02>
		<_03>0</_03>
		<_10>0</_10>
		<_11>0</_11>
		<_12>1</_12>
		<_13>0</_13>
		<_20>0</_20>
		<_21>1</_21>
		<_22>0</_22>
		<_23>0</_23>
		<_30>30</_30>
		<_31>-80</_31>
		<_32>60</_32>
		<_33>1</_33>
	</MovementregisterToArticulatorTransformation>
	<ArticulatorOnlyShowDecorationMeshes>true</ArticulatorOnlyShowDecorationMeshes>
	<ArticulationPlaneIncisalNeedleMarkerLengthY>37</ArticulationPlaneIncisalNeedleMarkerLengthY>
	<CollapseBennettAngle>true</CollapseBennettAngle>
	<CollapseHeightIncisalNeedleOffset>false</CollapseHeightIncisalNeedleOffset>
	<CollapseTiltCondylarGuide>false</CollapseTiltCondylarGuide>
	<CollapseRotationAxis>true</CollapseRotationAxis>
	<CollapseRotationFrontplateY>true</CollapseRotationFrontplateY>
	<CollapseRotationFrontplateZ>true</CollapseRotationFrontplateZ>
	<CollapseTiltFrontplate>true</CollapseTiltFrontplate>
	<CollapseImmediateSideshift>true</CollapseImmediateSideshift>
	<FrontplateAdjustable>false</FrontplateAdjustable>
	<IncisalNeedleRotation>false</IncisalNeedleRotation>
	<ExecuteRetrusionWithZeroBennettAngle>false</ExecuteRetrusionWithZeroBennettAngle>
	<RotationPointShift>1.2</RotationPointShift>
	<ShowArticulatorMeshes>true</ShowArticulatorMeshes>
	<BennettAngleLeftParam>
		<Type>BennettAngleLeft</Type>
		<Value>0</Value>
		<MinValue>0</MinValue>
		<MaxValue>0</MaxValue>
	</BennettAngleLeftParam>
	<BennettAngleRightParam>
		<Type>BennettAngleRight</Type>
		<Value>0</Value>
		<MinValue>0</MinValue>
		<MaxValue>0</MaxValue>
	</BennettAngleRightParam>
	<TiltCondylarGuideLeftParam>
		<Type>TiltCondylarGuideLeft</Type>
		<Value>15</Value>
		<MinValue>0</MinValue>
		<MaxValue>65</MaxValue>
	</TiltCondylarGuideLeftParam>
	<TiltCondylarGuideRightParam>
		<Type>TiltCondylarGuideRight</Type>
		<Value>15</Value>
		<MinValue>0</MinValue>
		<MaxValue>65</MaxValue>
	</TiltCondylarGuideRightParam>
	<HeightIncisalNeedleOffsetParam>
		<Type>HeightIncisalNeedleOffset</Type>
		<Value>0</Value>
		<MinValue>-5</MinValue>
		<MaxValue>10</MaxValue>
	</HeightIncisalNeedleOffsetParam>
	<ProtrusionParam>
		<Type>Protrusion</Type>
		<Value>5</Value>
		<MinValue>0</MinValue>
		<MaxValue>10</MaxValue>
	</ProtrusionParam>
	<RetrusionParam>
		<Type>Retrusion</Type>
		<Value>0</Value>
		<MinValue>0</MinValue>
		<MaxValue>0</MaxValue>
	</RetrusionParam>
	<LaterotrusionRightParam>
		<Type>LaterotrusionRight</Type>
		<Value>5</Value>
		<MinValue>0</MinValue>
		<MaxValue>10</MaxValue>
	</LaterotrusionRightParam>
	<LaterotrusionLeftParam>
		<Type>LaterotrusionLeft</Type>
		<Value>5</Value>
		<MinValue>0</MinValue>
		<MaxValue>10</MaxValue>
	</LaterotrusionLeftParam>	
	<ShowArticulatorMeshes>true</ShowArticulatorMeshes>
	<CurrentBennettInsertColorLeft>BennettInsertSilver</CurrentBennettInsertColorLeft>
	<CurrentBennettInsertColorRight>BennettInsertSilver</CurrentBennettInsertColorRight>
	<CurrentCondylarInsertColorLeft>CondylarInsertMetal</CurrentCondylarInsertColorLeft>
	<CurrentCondylarInsertColorRight>CondylarInsertMetal</CurrentCondylarInsertColorRight>
	<ArticulatorMainParts>
		<Incisalneedle>
			<Filename>incisal_head.sdfa</Filename>
			<RenderEffectFile>silver</RenderEffectFile>
		</Incisalneedle>
		<Frontplate>
			<Filename>incisal_plate.sdfa</Filename>
		</Frontplate>
	</ArticulatorMainParts>
	<ArticulatorDecorations>
		<DecorationMeshes>
			<!-- INCISAL TABLE DECORATIONS -->
			<ArticulatorDecorationMesh>
				<Type>FrontplateAdjustableAroundXYAxisRightDecorations</Type>
				<Filename>incisal_plate.sdfa</Filename>
				<RenderEffectFile>plastic_yellow</RenderEffectFile>
			</ArticulatorDecorationMesh>
			<!-- DECORATION MESHES -->
			<!--Upper-->
			<ArticulatorDecorationMesh>
				<Type>UpperPartDecorations</Type>
				<Filename>upper_part_plastic.sdfa</Filename>
				<RenderEffectFile>plastic_grey</RenderEffectFile>
			</ArticulatorDecorationMesh>
			<ArticulatorDecorationMesh>
				<Type>UpperPartDecorations</Type>
				<Filename>upper_part_plastic_yellow.sdfa</Filename>
				<RenderEffectFile>plastic_yellow</RenderEffectFile>
			</ArticulatorDecorationMesh>
			<ArticulatorDecorationMesh>
				<Type>UpperPartDecorations</Type>
				<Filename>upper_decals_grey.sdfa</Filename>
				<ColorAmbient>#000000</ColorAmbient>
				<ColorDiffuse>#c4cdc8</ColorDiffuse>
				<ColorSpecular>#000000</ColorSpecular>
				<ColorEmissive>#000000</ColorEmissive>
				<ColorShininess>0</ColorShininess>
				<RenderEffectFile>plastic</RenderEffectFile>
			</ArticulatorDecorationMesh>
			<ArticulatorDecorationMesh>
				<Type>UpperPartDecorations</Type>
				<Filename>incisal_needle_decals.sdfa</Filename>
				<ColorAmbient>#ffffff</ColorAmbient>
				<ColorDiffuse>#ffffff</ColorDiffuse>
				<ColorSpecular>#000000</ColorSpecular>
				<ColorEmissive>#000000</ColorEmissive>
				<ColorShininess>0</ColorShininess>
			</ArticulatorDecorationMesh>
			<ArticulatorDecorationMesh>
				<Type>UpperPartDecorations</Type>
				<Filename>upper_part_metal_incisal_needle.sdfa</Filename>
				<ColorAmbient>#000000</ColorAmbient>
				<ColorDiffuse>#000000</ColorDiffuse>
				<ColorSpecular>#000000</ColorSpecular>
				<ColorEmissive>#000000</ColorEmissive>
				<ColorShininess>0</ColorShininess>
				<RenderEffectFile>plastic</RenderEffectFile>
			</ArticulatorDecorationMesh>
			<ArticulatorDecorationMesh>
				<Type>UpperPartDecorations</Type>
				<Filename>upper_parts_metal_anodized.sdfa</Filename>
				<ColorAmbient>#FFFFFF</ColorAmbient>
				<ColorDiffuse>#aaaaae</ColorDiffuse>
				<ColorSpecular>#FFFFFF</ColorSpecular>
				<ColorEmissive>#404040</ColorEmissive>
				<ColorShininess>8.0</ColorShininess>
				<RenderEffectFile>silver</RenderEffectFile>
			</ArticulatorDecorationMesh>
			<ArticulatorDecorationMesh>
				<Type>UpperPartDecorations</Type>
				<Filename>upper_part_metal_polished.sdfa</Filename>
				<ColorAmbient>#ededed</ColorAmbient>
				<ColorDiffuse>#bebebe</ColorDiffuse>
				<ColorSpecular>#FFFFFF</ColorSpecular>
				<ColorEmissive>#404040</ColorEmissive>
				<ColorShininess>8.0</ColorShininess>
				<RenderEffectFile>silver</RenderEffectFile>
			</ArticulatorDecorationMesh>
			<ArticulatorDecorationMesh>
				<Type>UpperPartDecorations</Type>
				<Filename>upper_decals_left_grey.sdfa</Filename>
				<ColorAmbient>#000000</ColorAmbient>
				<ColorDiffuse>#c4cdc8</ColorDiffuse>
				<ColorSpecular>#000000</ColorSpecular>
				<ColorEmissive>#000000</ColorEmissive>
				<ColorShininess>0</ColorShininess>
				<RenderEffectFile>plastic</RenderEffectFile>
			</ArticulatorDecorationMesh>
			<ArticulatorDecorationMesh>
				<Type>UpperPartDecorations</Type>
				<Filename>upper_decals_right_grey.sdfa</Filename>
				<ColorAmbient>#000000</ColorAmbient>
				<ColorDiffuse>#c4cdc8</ColorDiffuse>
				<ColorSpecular>#000000</ColorSpecular>
				<ColorEmissive>#000000</ColorEmissive>
				<ColorShininess>0</ColorShininess>
				<RenderEffectFile>plastic</RenderEffectFile>
			</ArticulatorDecorationMesh>
			<ArticulatorDecorationMesh>
				<Type>UpperPartDecorations</Type>
				<Filename>upper_decals_back_grey.sdfa</Filename>
				<ColorAmbient>#000000</ColorAmbient>
				<ColorDiffuse>#c4cdc8</ColorDiffuse>
				<ColorSpecular>#000000</ColorSpecular>
				<ColorEmissive>#000000</ColorEmissive>
				<ColorShininess>0</ColorShininess>
				<RenderEffectFile>plastic</RenderEffectFile>
			</ArticulatorDecorationMesh>
			<!--Lower-->
			<ArticulatorDecorationMesh>
				<Type>LowerPartDecorations</Type>
				<Filename>lower_part_metal_polished.sdfa</Filename>
				<ColorAmbient>#ededed</ColorAmbient>
				<ColorDiffuse>#bebebe</ColorDiffuse>
				<ColorSpecular>#FFFFFF</ColorSpecular>
				<ColorEmissive>#404040</ColorEmissive>
				<ColorShininess>8.0</ColorShininess>
				<RenderEffectFile>silver</RenderEffectFile>
			</ArticulatorDecorationMesh>
			<ArticulatorDecorationMesh>
				<Type>LowerPartDecorations</Type>
				<Filename>lower_part_plastic_grey.sdfa</Filename>
				<RenderEffectFile>plastic_grey</RenderEffectFile>
			</ArticulatorDecorationMesh>
			<ArticulatorDecorationMesh>
				<Type>LowerPartDecorations</Type>
				<Filename>lower_part_plastic_black.sdfa</Filename>
				<RenderEffectFile>plastic_black</RenderEffectFile>
			</ArticulatorDecorationMesh>
			<ArticulatorDecorationMesh>
				<Type>LowerPartDecorations</Type>
				<Filename>lower_part_decals.sdfa</Filename>
				<ColorAmbient>#000000</ColorAmbient>
				<ColorDiffuse>#000000</ColorDiffuse>
				<ColorSpecular>#000000</ColorSpecular>
				<ColorEmissive>#000000</ColorEmissive>
				<ColorShininess>8.0</ColorShininess>
			</ArticulatorDecorationMesh>
			<ArticulatorDecorationMesh>
				<Type>LowerPartDecorations</Type>
				<Filename>lower_parts_metal_black.sdfa</Filename>
				<RenderEffectFile>plastic_black</RenderEffectFile>
			</ArticulatorDecorationMesh>
			<ArticulatorDecorationMesh>
				<Type>LowerPartDecorations</Type>
				<Filename>lower_part_plastic_yellow.sdfa</Filename>
				<RenderEffectFile>plastic_yellow</RenderEffectFile>
			</ArticulatorDecorationMesh>
			<ArticulatorDecorationMesh>
				<Type>LowerPartDecorations</Type>
				<Filename>lower_part_metal_silver.sdfa</Filename>
				<ColorAmbient>#ededed</ColorAmbient>
				<ColorDiffuse>#bebebe</ColorDiffuse>
				<ColorSpecular>#FFFFFF</ColorSpecular>
				<ColorEmissive>#404040</ColorEmissive>
				<ColorShininess>8.0</ColorShininess>
				<RenderEffectFile>silver</RenderEffectFile>
			</ArticulatorDecorationMesh>
			<ArticulatorDecorationMesh>
				<Type>LowerPartDecorations</Type>
				<Filename>lower_parts_metal.sdfa</Filename>
				<ColorAmbient>#FFFFFF</ColorAmbient>
				<ColorDiffuse>#aaaaae</ColorDiffuse>
				<ColorSpecular>#FFFFFF</ColorSpecular>
				<ColorEmissive>#404040</ColorEmissive>
				<ColorShininess>8.0</ColorShininess>
				<RenderEffectFile>silver</RenderEffectFile>
			</ArticulatorDecorationMesh>
			<!--Right-->
			<ArticulatorDecorationMesh>
				<Type>CondylarguideRightDecorations</Type>
				<Filename>right_parts_grey.sdfa</Filename>
				<RenderEffectFile>plastic_grey</RenderEffectFile>
			</ArticulatorDecorationMesh>
			<ArticulatorDecorationMesh>
				<Type>CondylarguideRightDecorations</Type>
				<Filename>right_parts_yellow.sdfa</Filename>
				<RenderEffectFile>plastic_yellow</RenderEffectFile>
			</ArticulatorDecorationMesh>
			<ArticulatorDecorationMesh>
				<Type>CondylarguideRightDecorations</Type>
				<Filename>right_parts_black.sdfa</Filename>
				<RenderEffectFile>plastic_black</RenderEffectFile>
			</ArticulatorDecorationMesh>
			<ArticulatorDecorationMesh>
				<Type>CondylarguideRightDecorations</Type>
				<Filename>right_parts_metal.sdfa</Filename>
				<ColorAmbient>#ededed</ColorAmbient>
				<ColorDiffuse>#bebebe</ColorDiffuse>
				<ColorSpecular>#FFFFFF</ColorSpecular>
				<ColorEmissive>#404040</ColorEmissive>
				<ColorShininess>8.0</ColorShininess>
				<RenderEffectFile>silver</RenderEffectFile>
			</ArticulatorDecorationMesh>
			<!--Left-->
			<ArticulatorDecorationMesh>
				<Type>CondylarguideLeftDecorations</Type>
				<Filename>left_parts_grey.sdfa</Filename>
				<RenderEffectFile>plastic_grey</RenderEffectFile>
			</ArticulatorDecorationMesh>
			<ArticulatorDecorationMesh>
				<Type>CondylarguideLeftDecorations</Type>
				<Filename>left_parts_yellow.sdfa</Filename>
				<RenderEffectFile>plastic_yellow</RenderEffectFile>
			</ArticulatorDecorationMesh>
			<ArticulatorDecorationMesh>
				<Type>CondylarguideLeftDecorations</Type>
				<Filename>left_parts_black.sdfa</Filename>
				<RenderEffectFile>plastic_black</RenderEffectFile>
			</ArticulatorDecorationMesh>
			<ArticulatorDecorationMesh>
				<Type>CondylarguideLeftDecorations</Type>
				<Filename>left_parts_metal.sdfa</Filename>
				<ColorAmbient>#ededed</ColorAmbient>
				<ColorDiffuse>#bebebe</ColorDiffuse>
				<ColorSpecular>#FFFFFF</ColorSpecular>
				<ColorEmissive>#404040</ColorEmissive>
				<ColorShininess>8.0</ColorShininess>
				<RenderEffectFile>silver</RenderEffectFile>
			</ArticulatorDecorationMesh>
			<ArticulatorDecorationMesh>
				<Type>IncisalNeedleDecorations</Type>
				<Filename>incisal_needle.sdfa</Filename>
				<ColorAmbient>#ededed</ColorAmbient>
				<ColorDiffuse>#bebebe</ColorDiffuse>
				<ColorSpecular>#FFFFFF</ColorSpecular>
				<ColorEmissive>#404040</ColorEmissive>
				<ColorShininess>8.0</ColorShininess>
				<RenderEffectFile>silver</RenderEffectFile>
			</ArticulatorDecorationMesh>
		</DecorationMeshes>
	</ArticulatorDecorations>
	<FullDentureParamOverride>
		<Param>
			<Type>TiltCondylarGuideLeft</Type>
			<Value>30</Value>
		</Param>
		<Param>
			<Type>TiltCondylarGuideRight</Type>
			<Value>30</Value>
		</Param>
	</FullDentureParamOverride>
	<FullDentureSingleArchParamOverride>
		<Param>
			<Type>TiltCondylarGuideLeft</Type>
			<Value>30</Value>
		</Param>
		<Param>
			<Type>TiltCondylarGuideRight</Type>
			<Value>30</Value>
		</Param>
	</FullDentureSingleArchParamOverride>
</ArticulatorSettings>