<?xml version="1.0" encoding="utf-8"?>
<ToothBow xmlns:xsi="http://www.w3.org/2001/XMLSchema-instance" xmlns:xsd="http://www.w3.org/2001/XMLSchema">
  <ModelTeeth>
    <ModelTooth>
      <Number>18</Number>
      <Position>
        <x>-24.77458381652832</x>
        <y>-21.98561668395996</y>
        <z>-6.9610915184021</z>
      </Position>
      <AxisOcclusal>
        <x>-0.12813761414260247</x>
        <y>-0.06664868227792514</y>
        <z>0.9895143783657</z>
      </AxisOcclusal>
      <AxisMesial>
        <x>0.05611972249512764</x>
        <y>0.9956534041299181</y>
        <z>0.07432950687025977</z>
      </AxisMesial>
      <BuccoocclusalCusp1>
        <x>0</x>
        <y>0</y>
        <z>0</z>
      </BuccoocclusalCusp1>
      <BuccoocclusalCusp2>
        <x>0</x>
        <y>0</y>
        <z>0</z>
      </BuccoocclusalCusp2>
      <LinguoocclusalCusp1>
        <x>0</x>
        <y>0</y>
        <z>0</z>
      </LinguoocclusalCusp1>
      <LinguoocclusalCusp2>
        <x>0</x>
        <y>0</y>
        <z>0</z>
      </LinguoocclusalCusp2>
      <AntagonistCuspContact1>
        <x>0</x>
        <y>0</y>
        <z>0</z>
      </AntagonistCuspContact1>
      <AntagonistCuspContact2>
        <x>0</x>
        <y>0</y>
        <z>0</z>
      </AntagonistCuspContact2>
      <ContactPoint1>
        <x>0</x>
        <y>0</y>
        <z>0</z>
      </ContactPoint1>
      <ContactPoint2>
        <x>0</x>
        <y>0</y>
        <z>0</z>
      </ContactPoint2>
      <BuccalPoint>
        <x>0</x>
        <y>0</y>
        <z>0</z>
      </BuccalPoint>
      <BuccocervicalPoint>
        <x>0</x>
        <y>0</y>
        <z>0</z>
      </BuccocervicalPoint>
      <LingualPoint>
        <x>0</x>
        <y>0</y>
        <z>0</z>
      </LingualPoint>
      <LinguocervicalPoint>
        <x>0</x>
        <y>0</y>
        <z>0</z>
      </LinguocervicalPoint>
    </ModelTooth>
    <ModelTooth>
      <Number>17</Number>
      <Position>
        <x>-24.051546096801758</x>
        <y>-12.148012161254883</y>
        <z>-6.233336448669434</z>
      </Position>
      <AxisOcclusal>
        <x>-0.18038770738496093</x>
        <y>-0.05457137129360828</y>
        <z>0.9820805671937171</z>
      </AxisOcclusal>
      <AxisMesial>
        <x>0.10543772497700143</x>
        <y>0.9916336355986</y>
        <z>0.07446891231364602</z>
      </AxisMesial>
      <BuccoocclusalCusp1>
        <x>0</x>
        <y>0</y>
        <z>0</z>
      </BuccoocclusalCusp1>
      <BuccoocclusalCusp2>
        <x>0</x>
        <y>0</y>
        <z>0</z>
      </BuccoocclusalCusp2>
      <LinguoocclusalCusp1>
        <x>0</x>
        <y>0</y>
        <z>0</z>
      </LinguoocclusalCusp1>
      <LinguoocclusalCusp2>
        <x>0</x>
        <y>0</y>
        <z>0</z>
      </LinguoocclusalCusp2>
      <AntagonistCuspContact1>
        <x>0</x>
        <y>0</y>
        <z>0</z>
      </AntagonistCuspContact1>
      <AntagonistCuspContact2>
        <x>0</x>
        <y>0</y>
        <z>0</z>
      </AntagonistCuspContact2>
      <ContactPoint1>
        <x>0</x>
        <y>0</y>
        <z>0</z>
      </ContactPoint1>
      <ContactPoint2>
        <x>0</x>
        <y>0</y>
        <z>0</z>
      </ContactPoint2>
      <BuccalPoint>
        <x>0</x>
        <y>0</y>
        <z>0</z>
      </BuccalPoint>
      <BuccocervicalPoint>
        <x>0</x>
        <y>0</y>
        <z>0</z>
      </BuccocervicalPoint>
      <LingualPoint>
        <x>0</x>
        <y>0</y>
        <z>0</z>
      </LingualPoint>
      <LinguocervicalPoint>
        <x>0</x>
        <y>0</y>
        <z>0</z>
      </LinguocervicalPoint>
    </ModelTooth>
    <ModelTooth>
      <Number>16</Number>
      <Position>
        <x>-23.013381958007812</x>
        <y>-1.9301409721374512</y>
        <z>-5.859644412994385</z>
      </Position>
      <AxisOcclusal>
        <x>-0.20068441200232456</x>
        <y>0.014952143556509898</y>
        <z>0.9795418317674579</z>
      </AxisOcclusal>
      <AxisMesial>
        <x>0.20772258737445737</x>
        <y>0.9777974286862289</y>
        <z>0.027631777884532187</z>
      </AxisMesial>
      <BuccoocclusalCusp1>
        <x>0</x>
        <y>0</y>
        <z>0</z>
      </BuccoocclusalCusp1>
      <BuccoocclusalCusp2>
        <x>0</x>
        <y>0</y>
        <z>0</z>
      </BuccoocclusalCusp2>
      <LinguoocclusalCusp1>
        <x>0</x>
        <y>0</y>
        <z>0</z>
      </LinguoocclusalCusp1>
      <LinguoocclusalCusp2>
        <x>0</x>
        <y>0</y>
        <z>0</z>
      </LinguoocclusalCusp2>
      <AntagonistCuspContact1>
        <x>0</x>
        <y>0</y>
        <z>0</z>
      </AntagonistCuspContact1>
      <AntagonistCuspContact2>
        <x>0</x>
        <y>0</y>
        <z>0</z>
      </AntagonistCuspContact2>
      <ContactPoint1>
        <x>0</x>
        <y>0</y>
        <z>0</z>
      </ContactPoint1>
      <ContactPoint2>
        <x>0</x>
        <y>0</y>
        <z>0</z>
      </ContactPoint2>
      <BuccalPoint>
        <x>0</x>
        <y>0</y>
        <z>0</z>
      </BuccalPoint>
      <BuccocervicalPoint>
        <x>0</x>
        <y>0</y>
        <z>0</z>
      </BuccocervicalPoint>
      <LingualPoint>
        <x>0</x>
        <y>0</y>
        <z>0</z>
      </LingualPoint>
      <LinguocervicalPoint>
        <x>0</x>
        <y>0</y>
        <z>0</z>
      </LinguocervicalPoint>
    </ModelTooth>
    <ModelTooth>
      <Number>15</Number>
      <Position>
        <x>-21.853684895150987</x>
        <y>7.048099661481796</y>
        <z>-5.273955941097329</z>
      </Position>
      <AxisOcclusal>
        <x>-0.10643963698260453</x>
        <y>0.0201951138412587</y>
        <z>0.99411405837356</z>
      </AxisOcclusal>
      <AxisMesial>
        <x>0.21776364652599609</x>
        <y>0.9759952981168586</y>
        <z>0.0034888831286937674</z>
      </AxisMesial>
      <BuccoocclusalCusp1>
        <x>0</x>
        <y>0</y>
        <z>0</z>
      </BuccoocclusalCusp1>
      <BuccoocclusalCusp2>
        <x>0</x>
        <y>0</y>
        <z>0</z>
      </BuccoocclusalCusp2>
      <LinguoocclusalCusp1>
        <x>0</x>
        <y>0</y>
        <z>0</z>
      </LinguoocclusalCusp1>
      <LinguoocclusalCusp2>
        <x>0</x>
        <y>0</y>
        <z>0</z>
      </LinguoocclusalCusp2>
      <AntagonistCuspContact1>
        <x>0</x>
        <y>0</y>
        <z>0</z>
      </AntagonistCuspContact1>
      <AntagonistCuspContact2>
        <x>0</x>
        <y>0</y>
        <z>0</z>
      </AntagonistCuspContact2>
      <ContactPoint1>
        <x>0</x>
        <y>0</y>
        <z>0</z>
      </ContactPoint1>
      <ContactPoint2>
        <x>0</x>
        <y>0</y>
        <z>0</z>
      </ContactPoint2>
      <BuccalPoint>
        <x>0</x>
        <y>0</y>
        <z>0</z>
      </BuccalPoint>
      <BuccocervicalPoint>
        <x>0</x>
        <y>0</y>
        <z>0</z>
      </BuccocervicalPoint>
      <LingualPoint>
        <x>0</x>
        <y>0</y>
        <z>0</z>
      </LingualPoint>
      <LinguocervicalPoint>
        <x>0</x>
        <y>0</y>
        <z>0</z>
      </LinguocervicalPoint>
    </ModelTooth>
    <ModelTooth>
      <Number>14</Number>
      <Position>
        <x>-19.91795938391057</x>
        <y>14.157651278633761</y>
        <z>-5.132012086763858</z>
      </Position>
      <AxisOcclusal>
        <x>-0.07449725844499025</x>
        <y>0.04869102574989769</y>
        <z>0.9960317979339832</z>
      </AxisOcclusal>
      <AxisMesial>
        <x>0.3126604776485567</x>
        <y>0.9495855927244641</y>
        <z>-0.0230353599213126</z>
      </AxisMesial>
      <BuccoocclusalCusp1>
        <x>0</x>
        <y>0</y>
        <z>0</z>
      </BuccoocclusalCusp1>
      <BuccoocclusalCusp2>
        <x>0</x>
        <y>0</y>
        <z>0</z>
      </BuccoocclusalCusp2>
      <LinguoocclusalCusp1>
        <x>0</x>
        <y>0</y>
        <z>0</z>
      </LinguoocclusalCusp1>
      <LinguoocclusalCusp2>
        <x>0</x>
        <y>0</y>
        <z>0</z>
      </LinguoocclusalCusp2>
      <AntagonistCuspContact1>
        <x>0</x>
        <y>0</y>
        <z>0</z>
      </AntagonistCuspContact1>
      <AntagonistCuspContact2>
        <x>0</x>
        <y>0</y>
        <z>0</z>
      </AntagonistCuspContact2>
      <ContactPoint1>
        <x>0</x>
        <y>0</y>
        <z>0</z>
      </ContactPoint1>
      <ContactPoint2>
        <x>0</x>
        <y>0</y>
        <z>0</z>
      </ContactPoint2>
      <BuccalPoint>
        <x>0</x>
        <y>0</y>
        <z>0</z>
      </BuccalPoint>
      <BuccocervicalPoint>
        <x>0</x>
        <y>0</y>
        <z>0</z>
      </BuccocervicalPoint>
      <LingualPoint>
        <x>0</x>
        <y>0</y>
        <z>0</z>
      </LingualPoint>
      <LinguocervicalPoint>
        <x>0</x>
        <y>0</y>
        <z>0</z>
      </LinguocervicalPoint>
    </ModelTooth>
    <ModelTooth>
      <Number>13</Number>
      <Position>
        <x>-17.66393280029297</x>
        <y>21.693532943725586</y>
        <z>-5.77187967300415</z>
      </Position>
      <AxisOcclusal>
        <x>-0.1531058135194774</x>
        <y>0.12742096454902815</y>
        <z>0.9799604622942368</z>
      </AxisOcclusal>
      <AxisMesial>
        <x>0.5191535716324709</x>
        <y>0.8541559789054056</y>
        <z>-0.0299521745687595</z>
      </AxisMesial>
      <BuccoocclusalCusp1>
        <x>0</x>
        <y>0</y>
        <z>0</z>
      </BuccoocclusalCusp1>
      <BuccoocclusalCusp2>
        <x>0</x>
        <y>0</y>
        <z>0</z>
      </BuccoocclusalCusp2>
      <LinguoocclusalCusp1>
        <x>0</x>
        <y>0</y>
        <z>0</z>
      </LinguoocclusalCusp1>
      <LinguoocclusalCusp2>
        <x>0</x>
        <y>0</y>
        <z>0</z>
      </LinguoocclusalCusp2>
      <AntagonistCuspContact1>
        <x>0</x>
        <y>0</y>
        <z>0</z>
      </AntagonistCuspContact1>
      <AntagonistCuspContact2>
        <x>0</x>
        <y>0</y>
        <z>0</z>
      </AntagonistCuspContact2>
      <ContactPoint1>
        <x>0</x>
        <y>0</y>
        <z>0</z>
      </ContactPoint1>
      <ContactPoint2>
        <x>0</x>
        <y>0</y>
        <z>0</z>
      </ContactPoint2>
      <BuccalPoint>
        <x>0</x>
        <y>0</y>
        <z>0</z>
      </BuccalPoint>
      <BuccocervicalPoint>
        <x>0</x>
        <y>0</y>
        <z>0</z>
      </BuccocervicalPoint>
      <LingualPoint>
        <x>0</x>
        <y>0</y>
        <z>0</z>
      </LingualPoint>
      <LinguocervicalPoint>
        <x>0</x>
        <y>0</y>
        <z>0</z>
      </LinguocervicalPoint>
    </ModelTooth>
    <ModelTooth>
      <Number>12</Number>
      <Position>
        <x>-12.186779975891113</x>
        <y>26.905597686767578</y>
        <z>-4.777240753173828</z>
      </Position>
      <AxisOcclusal>
        <x>-0.10857880003351357</x>
        <y>0.30271786138643947</y>
        <z>0.9468751451912245</z>
      </AxisOcclusal>
      <AxisMesial>
        <x>0.8580542125436649</x>
        <y>0.509493549180279</y>
        <z>-0.06449257073302157</z>
      </AxisMesial>
      <BuccoocclusalCusp1>
        <x>0</x>
        <y>0</y>
        <z>0</z>
      </BuccoocclusalCusp1>
      <BuccoocclusalCusp2>
        <x>0</x>
        <y>0</y>
        <z>0</z>
      </BuccoocclusalCusp2>
      <LinguoocclusalCusp1>
        <x>0</x>
        <y>0</y>
        <z>0</z>
      </LinguoocclusalCusp1>
      <LinguoocclusalCusp2>
        <x>0</x>
        <y>0</y>
        <z>0</z>
      </LinguoocclusalCusp2>
      <AntagonistCuspContact1>
        <x>0</x>
        <y>0</y>
        <z>0</z>
      </AntagonistCuspContact1>
      <AntagonistCuspContact2>
        <x>0</x>
        <y>0</y>
        <z>0</z>
      </AntagonistCuspContact2>
      <ContactPoint1>
        <x>0</x>
        <y>0</y>
        <z>0</z>
      </ContactPoint1>
      <ContactPoint2>
        <x>0</x>
        <y>0</y>
        <z>0</z>
      </ContactPoint2>
      <BuccalPoint>
        <x>0</x>
        <y>0</y>
        <z>0</z>
      </BuccalPoint>
      <BuccocervicalPoint>
        <x>0</x>
        <y>0</y>
        <z>0</z>
      </BuccocervicalPoint>
      <LingualPoint>
        <x>0</x>
        <y>0</y>
        <z>0</z>
      </LingualPoint>
      <LinguocervicalPoint>
        <x>0</x>
        <y>0</y>
        <z>0</z>
      </LinguocervicalPoint>
    </ModelTooth>
    <ModelTooth>
      <Number>11</Number>
      <Position>
        <x>-4.760544915340008</x>
        <y>30.121553971907048</y>
        <z>-4.675429783073687</z>
      </Position>
      <AxisOcclusal>
        <x>-0.00842636441672129</x>
        <y>0.35751056270073633</y>
        <z>0.933871079935619</z>
      </AxisOcclusal>
      <AxisMesial>
        <x>0.9992072223288666</x>
        <y>0.03934906516458701</y>
        <z>-0.00604796796486482</z>
      </AxisMesial>
      <BuccoocclusalCusp1>
        <x>0</x>
        <y>0</y>
        <z>0</z>
      </BuccoocclusalCusp1>
      <BuccoocclusalCusp2>
        <x>0</x>
        <y>0</y>
        <z>0</z>
      </BuccoocclusalCusp2>
      <LinguoocclusalCusp1>
        <x>0</x>
        <y>0</y>
        <z>0</z>
      </LinguoocclusalCusp1>
      <LinguoocclusalCusp2>
        <x>0</x>
        <y>0</y>
        <z>0</z>
      </LinguoocclusalCusp2>
      <AntagonistCuspContact1>
        <x>0</x>
        <y>0</y>
        <z>0</z>
      </AntagonistCuspContact1>
      <AntagonistCuspContact2>
        <x>0</x>
        <y>0</y>
        <z>0</z>
      </AntagonistCuspContact2>
      <ContactPoint1>
        <x>0</x>
        <y>0</y>
        <z>0</z>
      </ContactPoint1>
      <ContactPoint2>
        <x>0</x>
        <y>0</y>
        <z>0</z>
      </ContactPoint2>
      <BuccalPoint>
        <x>0</x>
        <y>0</y>
        <z>0</z>
      </BuccalPoint>
      <BuccocervicalPoint>
        <x>0</x>
        <y>0</y>
        <z>0</z>
      </BuccocervicalPoint>
      <LingualPoint>
        <x>0</x>
        <y>0</y>
        <z>0</z>
      </LingualPoint>
      <LinguocervicalPoint>
        <x>0</x>
        <y>0</y>
        <z>0</z>
      </LinguocervicalPoint>
    </ModelTooth>
    <ModelTooth>
      <Number>21</Number>
      <Position>
        <x>4.746717683049663</x>
        <y>30.122814884565948</y>
        <z>-4.674813702231382</z>
      </Position>
      <AxisOcclusal>
        <x>0.008210468234264369</x>
        <y>0.3575127180649476</y>
        <z>0.9338721778879524</z>
      </AxisOcclusal>
      <AxisMesial>
        <x>-0.9992168524315111</x>
        <y>0.0390835329052901</y>
        <z>-0.006177319200513301</z>
      </AxisMesial>
      <BuccoocclusalCusp1>
        <x>0</x>
        <y>0</y>
        <z>0</z>
      </BuccoocclusalCusp1>
      <BuccoocclusalCusp2>
        <x>0</x>
        <y>0</y>
        <z>0</z>
      </BuccoocclusalCusp2>
      <LinguoocclusalCusp1>
        <x>0</x>
        <y>0</y>
        <z>0</z>
      </LinguoocclusalCusp1>
      <LinguoocclusalCusp2>
        <x>0</x>
        <y>0</y>
        <z>0</z>
      </LinguoocclusalCusp2>
      <AntagonistCuspContact1>
        <x>0</x>
        <y>0</y>
        <z>0</z>
      </AntagonistCuspContact1>
      <AntagonistCuspContact2>
        <x>0</x>
        <y>0</y>
        <z>0</z>
      </AntagonistCuspContact2>
      <ContactPoint1>
        <x>0</x>
        <y>0</y>
        <z>0</z>
      </ContactPoint1>
      <ContactPoint2>
        <x>0</x>
        <y>0</y>
        <z>0</z>
      </ContactPoint2>
      <BuccalPoint>
        <x>0</x>
        <y>0</y>
        <z>0</z>
      </BuccalPoint>
      <BuccocervicalPoint>
        <x>0</x>
        <y>0</y>
        <z>0</z>
      </BuccocervicalPoint>
      <LingualPoint>
        <x>0</x>
        <y>0</y>
        <z>0</z>
      </LingualPoint>
      <LinguocervicalPoint>
        <x>0</x>
        <y>0</y>
        <z>0</z>
      </LinguocervicalPoint>
    </ModelTooth>
    <ModelTooth>
      <Number>22</Number>
      <Position>
        <x>12.173821449279785</x>
        <y>26.908836364746094</y>
        <z>-4.77566385269165</z>
      </Position>
      <AxisOcclusal>
        <x>0.10837578303331748</x>
        <y>0.30274669103820695</y>
        <z>0.9468891860811021</z>
      </AxisOcclusal>
      <AxisMesial>
        <x>-0.8581812800788173</x>
        <y>0.5092654123172814</y>
        <z>-0.06460364029674812</z>
      </AxisMesial>
      <BuccoocclusalCusp1>
        <x>0</x>
        <y>0</y>
        <z>0</z>
      </BuccoocclusalCusp1>
      <BuccoocclusalCusp2>
        <x>0</x>
        <y>0</y>
        <z>0</z>
      </BuccoocclusalCusp2>
      <LinguoocclusalCusp1>
        <x>0</x>
        <y>0</y>
        <z>0</z>
      </LinguoocclusalCusp1>
      <LinguoocclusalCusp2>
        <x>0</x>
        <y>0</y>
        <z>0</z>
      </LinguoocclusalCusp2>
      <AntagonistCuspContact1>
        <x>0</x>
        <y>0</y>
        <z>0</z>
      </AntagonistCuspContact1>
      <AntagonistCuspContact2>
        <x>0</x>
        <y>0</y>
        <z>0</z>
      </AntagonistCuspContact2>
      <ContactPoint1>
        <x>0</x>
        <y>0</y>
        <z>0</z>
      </ContactPoint1>
      <ContactPoint2>
        <x>0</x>
        <y>0</y>
        <z>0</z>
      </ContactPoint2>
      <BuccalPoint>
        <x>0</x>
        <y>0</y>
        <z>0</z>
      </BuccalPoint>
      <BuccocervicalPoint>
        <x>0</x>
        <y>0</y>
        <z>0</z>
      </BuccocervicalPoint>
      <LingualPoint>
        <x>0</x>
        <y>0</y>
        <z>0</z>
      </LingualPoint>
      <LinguocervicalPoint>
        <x>0</x>
        <y>0</y>
        <z>0</z>
      </LinguocervicalPoint>
    </ModelTooth>
    <ModelTooth>
      <Number>23</Number>
      <Position>
        <x>17.65248680114746</x>
        <y>21.698226928710938</y>
        <z>-5.769593238830566</z>
      </Position>
      <AxisOcclusal>
        <x>0.15294509798420233</x>
        <y>0.1274616392959624</y>
        <z>0.9799802689394255</z>
      </AxisOcclusal>
      <AxisMesial>
        <x>-0.5193766481391857</x>
        <y>0.8540179936443455</y>
        <z>-0.030019392055653352</z>
      </AxisMesial>
      <BuccoocclusalCusp1>
        <x>0</x>
        <y>0</y>
        <z>0</z>
      </BuccoocclusalCusp1>
      <BuccoocclusalCusp2>
        <x>0</x>
        <y>0</y>
        <z>0</z>
      </BuccoocclusalCusp2>
      <LinguoocclusalCusp1>
        <x>0</x>
        <y>0</y>
        <z>0</z>
      </LinguoocclusalCusp1>
      <LinguoocclusalCusp2>
        <x>0</x>
        <y>0</y>
        <z>0</z>
      </LinguoocclusalCusp2>
      <AntagonistCuspContact1>
        <x>0</x>
        <y>0</y>
        <z>0</z>
      </AntagonistCuspContact1>
      <AntagonistCuspContact2>
        <x>0</x>
        <y>0</y>
        <z>0</z>
      </AntagonistCuspContact2>
      <ContactPoint1>
        <x>0</x>
        <y>0</y>
        <z>0</z>
      </ContactPoint1>
      <ContactPoint2>
        <x>0</x>
        <y>0</y>
        <z>0</z>
      </ContactPoint2>
      <BuccalPoint>
        <x>0</x>
        <y>0</y>
        <z>0</z>
      </BuccalPoint>
      <BuccocervicalPoint>
        <x>0</x>
        <y>0</y>
        <z>0</z>
      </BuccocervicalPoint>
      <LingualPoint>
        <x>0</x>
        <y>0</y>
        <z>0</z>
      </LingualPoint>
      <LinguocervicalPoint>
        <x>0</x>
        <y>0</y>
        <z>0</z>
      </LinguocervicalPoint>
    </ModelTooth>
    <ModelTooth>
      <Number>24</Number>
      <Position>
        <x>19.908433830625178</x>
        <y>14.162942495324977</y>
        <z>-5.129433913720032</z>
      </Position>
      <AxisOcclusal>
        <x>0.07435537986967147</x>
        <y>0.04871080889340089</y>
        <z>0.9960414321610258</z>
      </AxisOcclusal>
      <AxisMesial>
        <x>-0.31290985058021237</x>
        <y>0.9495024647203043</y>
        <z>-0.023075851012179138</z>
      </AxisMesial>
      <BuccoocclusalCusp1>
        <x>0</x>
        <y>0</y>
        <z>0</z>
      </BuccoocclusalCusp1>
      <BuccoocclusalCusp2>
        <x>0</x>
        <y>0</y>
        <z>0</z>
      </BuccoocclusalCusp2>
      <LinguoocclusalCusp1>
        <x>0</x>
        <y>0</y>
        <z>0</z>
      </LinguoocclusalCusp1>
      <LinguoocclusalCusp2>
        <x>0</x>
        <y>0</y>
        <z>0</z>
      </LinguoocclusalCusp2>
      <AntagonistCuspContact1>
        <x>0</x>
        <y>0</y>
        <z>0</z>
      </AntagonistCuspContact1>
      <AntagonistCuspContact2>
        <x>0</x>
        <y>0</y>
        <z>0</z>
      </AntagonistCuspContact2>
      <ContactPoint1>
        <x>0</x>
        <y>0</y>
        <z>0</z>
      </ContactPoint1>
      <ContactPoint2>
        <x>0</x>
        <y>0</y>
        <z>0</z>
      </ContactPoint2>
      <BuccalPoint>
        <x>0</x>
        <y>0</y>
        <z>0</z>
      </BuccalPoint>
      <BuccocervicalPoint>
        <x>0</x>
        <y>0</y>
        <z>0</z>
      </BuccocervicalPoint>
      <LingualPoint>
        <x>0</x>
        <y>0</y>
        <z>0</z>
      </LingualPoint>
      <LinguocervicalPoint>
        <x>0</x>
        <y>0</y>
        <z>0</z>
      </LinguocervicalPoint>
    </ModelTooth>
    <ModelTooth>
      <Number>25</Number>
      <Position>
        <x>21.84606544447426</x>
        <y>7.053905074779479</y>
        <z>-5.271127485939803</z>
      </Position>
      <AxisOcclusal>
        <x>0.10630558724643913</x>
        <y>0.020223376413442285</y>
        <z>0.9941278273776617</z>
      </AxisOcclusal>
      <AxisMesial>
        <x>-0.21802341422580984</x>
        <y>0.9759374030177166</y>
        <z>0.0034606705067229643</z>
      </AxisMesial>
      <BuccoocclusalCusp1>
        <x>0</x>
        <y>0</y>
        <z>0</z>
      </BuccoocclusalCusp1>
      <BuccoocclusalCusp2>
        <x>0</x>
        <y>0</y>
        <z>0</z>
      </BuccoocclusalCusp2>
      <LinguoocclusalCusp1>
        <x>0</x>
        <y>0</y>
        <z>0</z>
      </LinguoocclusalCusp1>
      <LinguoocclusalCusp2>
        <x>0</x>
        <y>0</y>
        <z>0</z>
      </LinguoocclusalCusp2>
      <AntagonistCuspContact1>
        <x>0</x>
        <y>0</y>
        <z>0</z>
      </AntagonistCuspContact1>
      <AntagonistCuspContact2>
        <x>0</x>
        <y>0</y>
        <z>0</z>
      </AntagonistCuspContact2>
      <ContactPoint1>
        <x>0</x>
        <y>0</y>
        <z>0</z>
      </ContactPoint1>
      <ContactPoint2>
        <x>0</x>
        <y>0</y>
        <z>0</z>
      </ContactPoint2>
      <BuccalPoint>
        <x>0</x>
        <y>0</y>
        <z>0</z>
      </BuccalPoint>
      <BuccocervicalPoint>
        <x>0</x>
        <y>0</y>
        <z>0</z>
      </BuccocervicalPoint>
      <LingualPoint>
        <x>0</x>
        <y>0</y>
        <z>0</z>
      </LingualPoint>
      <LinguocervicalPoint>
        <x>0</x>
        <y>0</y>
        <z>0</z>
      </LinguocervicalPoint>
    </ModelTooth>
    <ModelTooth>
      <Number>26</Number>
      <Position>
        <x>23.008224487304688</x>
        <y>-1.9240258932113647</y>
        <z>-5.85666561126709</z>
      </Position>
      <AxisOcclusal>
        <x>0.2005536043330462</x>
        <y>0.015005455043046026</y>
        <z>0.9795678067943919</z>
      </AxisOcclusal>
      <AxisMesial>
        <x>-0.2079859967902678</x>
        <y>0.977742193203186</y>
        <z>0.027604868581152058</z>
      </AxisMesial>
      <BuccoocclusalCusp1>
        <x>0</x>
        <y>0</y>
        <z>0</z>
      </BuccoocclusalCusp1>
      <BuccoocclusalCusp2>
        <x>0</x>
        <y>0</y>
        <z>0</z>
      </BuccoocclusalCusp2>
      <LinguoocclusalCusp1>
        <x>0</x>
        <y>0</y>
        <z>0</z>
      </LinguoocclusalCusp1>
      <LinguoocclusalCusp2>
        <x>0</x>
        <y>0</y>
        <z>0</z>
      </LinguoocclusalCusp2>
      <AntagonistCuspContact1>
        <x>0</x>
        <y>0</y>
        <z>0</z>
      </AntagonistCuspContact1>
      <AntagonistCuspContact2>
        <x>0</x>
        <y>0</y>
        <z>0</z>
      </AntagonistCuspContact2>
      <ContactPoint1>
        <x>0</x>
        <y>0</y>
        <z>0</z>
      </ContactPoint1>
      <ContactPoint2>
        <x>0</x>
        <y>0</y>
        <z>0</z>
      </ContactPoint2>
      <BuccalPoint>
        <x>0</x>
        <y>0</y>
        <z>0</z>
      </BuccalPoint>
      <BuccocervicalPoint>
        <x>0</x>
        <y>0</y>
        <z>0</z>
      </BuccocervicalPoint>
      <LingualPoint>
        <x>0</x>
        <y>0</y>
        <z>0</z>
      </LingualPoint>
      <LinguocervicalPoint>
        <x>0</x>
        <y>0</y>
        <z>0</z>
      </LinguocervicalPoint>
    </ModelTooth>
    <ModelTooth>
      <Number>27</Number>
      <Position>
        <x>24.04915428161621</x>
        <y>-12.141621589660645</y>
        <z>-6.230222702026367</z>
      </Position>
      <AxisOcclusal>
        <x>0.1802750657955534</x>
        <y>-0.05452345176284165</y>
        <z>0.9821039119463245</z>
      </AxisOcclusal>
      <AxisMesial>
        <x>-0.10571088635491037</x>
        <y>0.9916055792535682</y>
        <z>0.07445524628429455</z>
      </AxisMesial>
      <BuccoocclusalCusp1>
        <x>0</x>
        <y>0</y>
        <z>0</z>
      </BuccoocclusalCusp1>
      <BuccoocclusalCusp2>
        <x>0</x>
        <y>0</y>
        <z>0</z>
      </BuccoocclusalCusp2>
      <LinguoocclusalCusp1>
        <x>0</x>
        <y>0</y>
        <z>0</z>
      </LinguoocclusalCusp1>
      <LinguoocclusalCusp2>
        <x>0</x>
        <y>0</y>
        <z>0</z>
      </LinguoocclusalCusp2>
      <AntagonistCuspContact1>
        <x>0</x>
        <y>0</y>
        <z>0</z>
      </AntagonistCuspContact1>
      <AntagonistCuspContact2>
        <x>0</x>
        <y>0</y>
        <z>0</z>
      </AntagonistCuspContact2>
      <ContactPoint1>
        <x>0</x>
        <y>0</y>
        <z>0</z>
      </ContactPoint1>
      <ContactPoint2>
        <x>0</x>
        <y>0</y>
        <z>0</z>
      </ContactPoint2>
      <BuccalPoint>
        <x>0</x>
        <y>0</y>
        <z>0</z>
      </BuccalPoint>
      <BuccocervicalPoint>
        <x>0</x>
        <y>0</y>
        <z>0</z>
      </BuccocervicalPoint>
      <LingualPoint>
        <x>0</x>
        <y>0</y>
        <z>0</z>
      </LingualPoint>
      <LinguocervicalPoint>
        <x>0</x>
        <y>0</y>
        <z>0</z>
      </LinguocervicalPoint>
    </ModelTooth>
    <ModelTooth>
      <Number>28</Number>
      <Position>
        <x>24.7748966217041</x>
        <y>-21.979034423828125</y>
        <z>-6.957884311676025</z>
      </Position>
      <AxisOcclusal>
        <x>0.12802722768978886</x>
        <y>-0.06661464127648623</y>
        <z>0.9895309588576157</z>
      </AxisOcclusal>
      <AxisMesial>
        <x>-0.05639393463565046</x>
        <y>0.9956384545894473</y>
        <z>0.07432221659131706</z>
      </AxisMesial>
      <BuccoocclusalCusp1>
        <x>0</x>
        <y>0</y>
        <z>0</z>
      </BuccoocclusalCusp1>
      <BuccoocclusalCusp2>
        <x>0</x>
        <y>0</y>
        <z>0</z>
      </BuccoocclusalCusp2>
      <LinguoocclusalCusp1>
        <x>0</x>
        <y>0</y>
        <z>0</z>
      </LinguoocclusalCusp1>
      <LinguoocclusalCusp2>
        <x>0</x>
        <y>0</y>
        <z>0</z>
      </LinguoocclusalCusp2>
      <AntagonistCuspContact1>
        <x>0</x>
        <y>0</y>
        <z>0</z>
      </AntagonistCuspContact1>
      <AntagonistCuspContact2>
        <x>0</x>
        <y>0</y>
        <z>0</z>
      </AntagonistCuspContact2>
      <ContactPoint1>
        <x>0</x>
        <y>0</y>
        <z>0</z>
      </ContactPoint1>
      <ContactPoint2>
        <x>0</x>
        <y>0</y>
        <z>0</z>
      </ContactPoint2>
      <BuccalPoint>
        <x>0</x>
        <y>0</y>
        <z>0</z>
      </BuccalPoint>
      <BuccocervicalPoint>
        <x>0</x>
        <y>0</y>
        <z>0</z>
      </BuccocervicalPoint>
      <LingualPoint>
        <x>0</x>
        <y>0</y>
        <z>0</z>
      </LingualPoint>
      <LinguocervicalPoint>
        <x>0</x>
        <y>0</y>
        <z>0</z>
      </LinguocervicalPoint>
    </ModelTooth>
  </ModelTeeth>
</ToothBow>